curl2pyreqs/__init__.py
curl2pyreqs/__main__.py
curl2pyreqs/common.py
curl2pyreqs/ulti.py
curl2pyreqs-0.4.1.dist-info/LICENSE
curl2pyreqs-0.4.1.dist-info/METADATA
curl2pyreqs-0.4.1.dist-info/WHEEL
curl2pyreqs-0.4.1.dist-info/entry_points.txt
curl2pyreqs-0.4.1.dist-info/top_level.txt
curl2pyreqs-0.4.1.dist-info/zip-safe
curl2pyreqs-0.4.1.dist-info/RECORD
