Metadata-Version: 2.1
Name: curl2pyreqs
Version: 0.4.1
Summary: A Library to Convert Curl to Python Requests File
Home-page: https://github.com/knightz1224/curl2pyreqs
Author: ZHANG HJ
Author-email: kngihtz1224@163.com
License: GPLv3
Platform: any
Classifier: Programming Language :: Python :: 3
Classifier: License :: OSI Approved :: MIT License
Requires-Python: >=3.6
Requires-Dist: pyperclip (>=1.8.0)
Requires-Dist: rich (>=9.13.0)
